{
	"info": {
		"_postman_id": "b27d2e03-00ed-444e-b2ee-7d388ea09716",
		"name": "Assignment2",
		"schema": "https://schema.getpostman.com/json/collection/v2.1.0/collection.json"
	},
	"item": [
		{
			"name": "GetAllDetails",
			"request": {
				"method": "GET",
				"header": [],
				"url": null
			},
			"response": []
		},
		{
			"name": "GetProductById",
			"request": {
				"method": "GET",
				"header": [],
				"url": {
					"raw": "localhost:3000/api/get/2",
					"host": [
						"localhost"
					],
					"port": "3000",
					"path": [
						"api",
						"get",
						"2"
					]
				}
			},
			"response": []
		},
		{
			"name": "Update_Product",
			"request": {
				"method": "GET",
				"header": [],
				"url": null
			},
			"response": []
		},
		{
			"name": "Delete_Product",
			"request": {
				"method": "DELETE",
				"header": [],
				"url": {
					"raw": "localhost:3000/api/delete/2",
					"host": [
						"localhost"
					],
					"port": "3000",
					"path": [
						"api",
						"delete",
						"2"
					]
				}
			},
			"response": []
		},
		{
			"name": "Get_Price",
			"request": {
				"method": "GET",
				"header": [],
				"url": {
					"raw": "http://localhost:3000/api/price?product_id=1&quantityToBuy=5",
					"protocol": "http",
					"host": [
						"localhost"
					],
					"port": "3000",
					"path": [
						"api",
						"price"
					],
					"query": [
						{
							"key": "product_id",
							"value": "1"
						},
						{
							"key": "quantityToBuy",
							"value": "5"
						}
					]
				}
			},
			"response": []
		},
		{
			"name": "Add_Product",
			"request": {
				"method": "POST",
				"header": [],
				"url": {
					"raw": "http://localhost:3000/api/add?id=3&name=Product%203&price=15&availableQuantity=100&manufacturer=manufacturer3",
					"protocol": "http",
					"host": [
						"localhost"
					],
					"port": "3000",
					"path": [
						"api",
						"add"
					],
					"query": [
						{
							"key": "id",
							"value": "3"
						},
						{
							"key": "name",
							"value": "Product%203"
						},
						{
							"key": "price",
							"value": "15"
						},
						{
							"key": "availableQuantity",
							"value": "100"
						},
						{
							"key": "manufacturer",
							"value": "manufacturer3"
						}
					]
				}
			},
			"response": []
		}
	]
}